odoo/addons/contract_forecast/README.rst
odoo/addons/contract_forecast/__init__.py
odoo/addons/contract_forecast/__manifest__.py
odoo/addons/contract_forecast/hooks.py
odoo/addons/contract_forecast/data/queue_job_channel.xml
odoo/addons/contract_forecast/data/queue_job_functions.xml
odoo/addons/contract_forecast/i18n/contract_forecast.pot
odoo/addons/contract_forecast/i18n/de.po
odoo/addons/contract_forecast/i18n/es.po
odoo/addons/contract_forecast/i18n/fr.po
odoo/addons/contract_forecast/i18n/it.po
odoo/addons/contract_forecast/i18n/pt.po
odoo/addons/contract_forecast/i18n/pt_BR.po
odoo/addons/contract_forecast/i18n/sv.po
odoo/addons/contract_forecast/models/__init__.py
odoo/addons/contract_forecast/models/contract.py
odoo/addons/contract_forecast/models/contract_line.py
odoo/addons/contract_forecast/models/contract_line_forecast_period.py
odoo/addons/contract_forecast/models/res_company.py
odoo/addons/contract_forecast/models/res_config_settings.py
odoo/addons/contract_forecast/readme/CONFIGURE.md
odoo/addons/contract_forecast/readme/CONTRIBUTORS.md
odoo/addons/contract_forecast/readme/DESCRIPTION.md
odoo/addons/contract_forecast/readme/USAGE.md
odoo/addons/contract_forecast/security/contract_line_forecast_period.xml
odoo/addons/contract_forecast/static/description/icon.png
odoo/addons/contract_forecast/static/description/index.html
odoo/addons/contract_forecast/tests/__init__.py
odoo/addons/contract_forecast/tests/test_contract_line_forecast_period.py
odoo/addons/contract_forecast/views/contract.xml
odoo/addons/contract_forecast/views/contract_line_forecast_period.xml
odoo/addons/contract_forecast/views/res_config_settings.xml
odoo_addon_contract_forecast-18.0.1.0.1.1.dist-info/METADATA
odoo_addon_contract_forecast-18.0.1.0.1.1.dist-info/WHEEL
odoo_addon_contract_forecast-18.0.1.0.1.1.dist-info/top_level.txt
odoo_addon_contract_forecast-18.0.1.0.1.1.dist-info/RECORD
